mkdocs_authors_plugin/__init__.py
mkdocs_authors_plugin/plugin.py
mkdocs_authors_plugin-0.1.0.dist-info/licenses/LICENSE
mkdocs_authors_plugin-0.1.0.dist-info/METADATA
mkdocs_authors_plugin-0.1.0.dist-info/WHEEL
mkdocs_authors_plugin-0.1.0.dist-info/entry_points.txt
mkdocs_authors_plugin-0.1.0.dist-info/top_level.txt
mkdocs_authors_plugin-0.1.0.dist-info/RECORD
