Metadata-Version: 2.4
Name: mkdocs-authors-plugin
Version: 0.1.0
Summary: A MkDocs plugin to generate an authors page from a YAML file.
Author-email: Thomas Zwagerman <thozwa@bas.ac.uk>
License: MIT License
Project-URL: Homepage, https://github.com/thomaszwagerman/mkdocs-authors-plugin
Keywords: mkdocs,plugin,authors,documentation
Classifier: Development Status :: 4 - Beta
Classifier: Intended Audience :: Developers
Classifier: Intended Audience :: Information Technology
Classifier: License :: OSI Approved :: MIT License
Classifier: Programming Language :: Python :: 3
Classifier: Programming Language :: Python :: 3.7
Classifier: Programming Language :: Python :: 3.8
Classifier: Programming Language :: Python :: 3.9
Classifier: Programming Language :: Python :: 3.10
Classifier: Programming Language :: Python :: 3.11
Classifier: Programming Language :: Python :: 3.12
Classifier: Operating System :: OS Independent
Classifier: Topic :: Documentation
Classifier: Topic :: Software Development :: Documentation
Requires-Python: >=3.7
License-File: LICENSE
Requires-Dist: mkdocs>=1.2
Requires-Dist: PyYAML>=5.1
Provides-Extra: tests
Requires-Dist: pytest; extra == "tests"
Requires-Dist: pytest-cov; extra == "tests"
Provides-Extra: docs
Requires-Dist: mkdocs; extra == "docs"
Requires-Dist: mkdocs-material; extra == "docs"
Dynamic: license-file
